HugSqlTool/__init__.py
ads_engine/__init__.py
ads_engine/ads_config.py
ads_engine/ads_manager.py
config_engine/__init__.py
config_engine/config_manager.py
constants_engine/__init__.py
constants_engine/constants.py
input_engine/__init__.py
input_engine/input_manager.py
input_engine/input_tip_constants.py
service_engine/__init__.py
service_engine/service_manager.py
sql_generator_test/SqlGeneratorForTestReport.py
sql_generator_test/__init__.py
tag_template_cons/__init__.py
tag_template_cons/tag_template_constants.py
tag_template_mana/__init__.py
tag_template_mana/tag_template_manager.py
template_engine/__init__.py
template_engine/template_config.py
template_engine/template_manager.py
template_engine/tag_templates/__init__.py
utils_engine/__init__.py
utils_engine/core_utils.py
utils_engine/git_utils.py
HugSqlTool-1.2.5.dist-info/LICENSE
HugSqlTool-1.2.5.dist-info/METADATA
HugSqlTool-1.2.5.dist-info/WHEEL
HugSqlTool-1.2.5.dist-info/top_level.txt
HugSqlTool-1.2.5.dist-info/RECORD
